binarytrees_nv/__init__.py
binarytrees_nv/binarytrees_nv.py
binarytrees_nv/exceptions.py
binarytrees_nv-0.1.4.dist-info/WHEEL
binarytrees_nv-0.1.4.dist-info/METADATA
binarytrees_nv-0.1.4.dist-info/RECORD
