Metadata-Version: 2.4
Name: binarytrees-nv
Version: 0.1.4
Summary: Package providing recursive and iterative binary tree generators.
Author: Anton Sibilev
Author-email: Anton Sibilev <antonsibilev0025@gmail.com>
License-Expression: MIT
Classifier: Programming Language :: Python :: 3
Classifier: License :: OSI Approved :: MIT License
Classifier: Operating System :: OS Independent
Requires-Python: >=3.9
Project-URL: Homepage, https://github.com/AntSib/Python-Herzen-Course/tree/main/%D0%A1%D0%B5%D0%BC%D0%B5%D1%81%D1%82%D1%80-5/LR-3
